Workbook
Name Slicer_Internet_Order: #N/A
Name Slicer_State1: #N/A
Name Диапазон1: '[8]СЧЕТЕСЛИ и СУММЕСЛИ'!$A$1:$D$7
Name Доставка__евро: '[9]продажи 2'!$F$2:$F$15
Name Доставка__евро: '[10]продажи 2'!$F$2:$F$15
Name Количество: '[9]продажи 2'!$D$2:$D$15
Name Количество: '[10]продажи 2'!$D$2:$D$15
Name Конфеты: [11]СУММ_МН!#REF!
Name Конфеты: #REF!
Name москва: #REF!
Name Оценки: '[12]упр.6-10'!$C$3:$F$12
Name Печенье: [11]СУММ_МН!#REF!
Name Печенье: #REF!
Name прайс: [13]Продажи2!$B$14:$D$17
Name Скидка: '[9]продажи 2'!$E$2:$E$15
Name Скидка: '[10]продажи 2'!$E$2:$E$15
Name угол: '[8]COS, SIN, TAN'!$A$2:$A$40
Name Цена__евро: '[9]продажи 2'!$C$2:$C$15
Name Цена__евро: '[10]продажи 2'!$C$2:$C$15

Sheet Данные 
A1: Сектор | B1: Регион | C1: Рынок сбыта | D1: Торговый представитель | E1: Товар | F1: Дата заказа | G1: День недели | H1: Заказчик | I1: Количество | J1: Доход | K1: Прибыль | L1: Цена
A2: Производство | B2: Средний Запад | C2: Детройт | D2: Генри | E2: Модуль | F2: 41640 | G2: Ср | H2: Ford | I2: 1000 | J2: 22810 | K2: 10220 | L2: 12590
A3: Связь | B3: Северо-Восток | C3: Нью-Йорк | D3: Руди | E3: Устройство | F3: 41641 | G3: Чт | H3: Verizon | I3: 100 | J3: 2257 | K3: 984 | L3: 1273
A4: Энергетика | B4: Юг | C4: Хьюстон | D4: Ред | E4: Модуль | F4: 41643 | G4: Сб | H4: Valero Energy | I4: 400 | J4: 9152 | K4: 4088 | L4: 5064
A5: Здравоохранение | B5: Средний Запад | C5: Луисвилл | D5: Крис | E5: Устройство | F5: 41643 | G5: Сб | H5: Cardinal Health | I5: 800 | J5: 18552 | K5: 7872 | L5: 10680
A6: Финансы | B6: Запад | C6: Северная Калифорния | D6: Карл | E6: Устройство | F6: 41646 | G6: Вт | H6: Wells Fargo | I6: 1000 | J6: 21730 | K6: 9840 | L6: 11890
A7: Производство | B7: Средний Запад | C7: Детройт | D7: Генри | E7: Деталь | F7: 41646 | G7: Вт | H7: General Motors | I7: 400 | J7: 8456 | K7: 3388 | L7: 5068
A8: Производство | B8: Средний Запад | C8: Детройт | D8: Генри | E8: Деталь | F8: 41648 | G8: Чт | H8: General Motors | I8: 800 | J8: 16416 | K8: 6776 | L8: 9640
A9: Розница | B9: Юг | C9: Новый Орлеан | D9: Сэм | E9: Модуль | F9: 41649 | G9: Пт | H9: Wal-Mart | I9: 900 | J9: 21438 | K9: 9198 | L9: 12240
A10: Производство | B10: Северо-Восток | C10: Нью-Йорк | D10: Руди | E10: Деталь | F10: 41651 | G10: Вс | H10: IBM | I10: 300 | J10: 6267 | K10: 2541 | L10: 3726
A11: Связь | B11: Юг | C11: Атланта | D11: Скарлетт | E11: Модуль | F11: 41653 | G11: Вт | H11: AT&T | I11: 100 | J11: 2401 | K11: 1022 | L11: 1379
A12: Связь | B12: Северо-Восток | C12: Нью-Йорк | D12: Руди | E12: Деталь | F12: 41654 | G12: Ср | H12: Verizon | I12: 500 | J12: 9345 | K12: 4235 | L12: 5110
A13: Финансы | B13: Северо-Восток | C13: Нью-Йорк | D13: Руди | E13: Деталь | F13: 41655 | G13: Чт | H13: CitiGroup | I13: 600 | J13: 11628 | K13: 5082 | L13: 6546
... A564: Производство | B564: Средний Запад | C564: Детройт | D564: Генри | E564: Деталь | F564: 42367 | G564: Вт | H564: General Motors | I564: 900 | J564: 15363 | K564: 7623 | L564: 7740
A565: Итог | L565: =SUBTOTAL(109,Таблица1[Цена]) -> 3729418

Sheet Ссылки
A1: Наименование | B1: Торговая марка | C1: Цена, евро | D1: Количество | E1: Доставка, евро | F1: Сумма, евро | G1: Сумма, руб. | H1: Сумма, доллары
A2: Кроссовки | B2: Adidas | C2: 100 | D2: 13 | E2: 20
A3: Кроссовки | B3: Puma | C3: 80 | D3: 15 | E3: 20
A4: Кроссовки | B4: Skechers | C4: 75 | D4: 30 | E4: 30
A5: Кроссовки | B5: Brooks | C5: 95 | D5: 24 | E5: 20
A6: Майка | B6: Nike | C6: 50 | D6: 15 | E6: 5
A7: Майка | B7: Adidas | C7: 45 | D7: 8 | E7: 5
A8: Майка | B8: Puma | C8: 39 | D8: 9 | E8: 5
A9: Майка | B9: Reebok | C9: 50 | D9: 28 | E9: 5
A10: Спортивный костюм | B10: Adidas | C10: 110 | D10: 25 | E10: 10
A11: Спортивный костюм | B11: Asics | C11: 85 | D11: 35 | E11: 10
A12: Мяч волейбольный | B12: Gala | C12: 52 | D12: 10 | E12: 10
A13: Велотренажер магнитный | B13: Kettler-Paso | C13: 500 | D13: 4 | E13: 30
... A15: Электрическая беговая дорожка | B15: Reebok-EK2 | C15: 1932 | D15: 2 | E15: 50

Sheet Курсы валют
A1: Курс доллара | B1: 65.1
A2: Курс евро | B2: 72.95

Sheet Смешаные ссылки
B2: Наименование | C2: Цена, р | D2: Количество
D3: 2 | E3: 3 | F3: 4 | G3: 5 | H3: 6
B4: Лакомка | C4: 205
B5: Ромашка | C5: 195
B6: Ласточка | C6: 189
B7: Буревестник | C7: 212
B8: Трюфель | C8: 234
B9: Левушка | C9: 186

Sheet Экспресс анализ
B4: Расходы | C4: июль | D4: август | E4: сентябрь | F4: ИТОГО
B5: реклама | C5: 21000 | D5: 25000 | E5: 27000
B6: аренда | C6: 55000 | D6: 55000 | E6: 56000
B7: оплата | C7: 9000 | D7: 10000 | E7: 11000
B8: налог | C8: 5000 | D8: 5500 | E8: 8000
B9: ИТОГО:
B11: Расходы | C11: июль | D11: август | E11: сентябрь | F11: СРЗНАЧ
B12: реклама | C12: 21000 | D12: 25000 | E12: 27000
B13: аренда | C13: 55000 | D13: 55000 | E13: 56000
B14: оплата | C14: 9000 | D14: 10000 | E14: 11000
B15: налог | C15: 5000 | D15: 5500 | E15: 8000
B16: Срзнач:
B18: Расходы | C18: июль | D18: август | E18: сентябрь | F18: МАКС
B19: реклама | C19: 21000 | D19: 25000 | E19: 27000
B20: аренда | C20: 55000 | D20: 55000 | E20: 56000
B21: оплата | C21: 9000 | D21: 10000 | E21: 11000
B22: налог | C22: 5000 | D22: 5500 | E22: 8000
B23: МАКС

Sheet Задание 1
A1: Задание: | B1: Заполнить столбец таблицы значениями начиная с "10" до "1000" с интервалом "10"
A3: Значения
A4: 10
A5: 20
A6: 30
A7: 40
A8: 50
A9: 60
A10: 70
A11: 80
A12: 90
A13: 100
A14: 110
A15: 120
... A103: 1000

Sheet Задание 2
A1: Задание: | B1: Вычислить стоимость в соответствующей иностранной валюте, после чего округлить до 2-х знаков
A2: наименование | B2: цена, руб. | C2: цена, евро | D2: цена, доллары
A3: Canon Digital ixus 900 Ti | B3: 13310.32 | C3: =ROUND(B3 / 'Курсы валют'!$B$1, 2) -> 204.46 | D3: =ROUND(B3 / 'Курсы валют'!$B$2, 2) -> 182.46
A4: Canon Digital ixus 800 IS | B4: 11148.37 | C4: =ROUND(B4 / 'Курсы валют'!$B$1, 2) -> 171.25 | D4: =ROUND(B4 / 'Курсы валют'!$B$2, 2) -> 152.82
A5: Canon PowerShot A640 | B5: 9898.09 | C5: =ROUND(B5 / 'Курсы валют'!$B$1, 2) -> 152.04 | D5: =ROUND(B5 / 'Курсы валют'!$B$2, 2) -> 135.68
A6: Kodak EasyShare Z650 | B6: 7475.66 | C6: =ROUND(B6 / 'Курсы валют'!$B$1, 2) -> 114.83 | D6: =ROUND(B6 / 'Курсы валют'!$B$2, 2) -> 102.48
A7: Kodak EasyShare C533 | B7: 3776.9 | C7: =ROUND(B7 / 'Курсы валют'!$B$1, 2) -> 58.02 | D7: =ROUND(B7 / 'Курсы валют'!$B$2, 2) -> 51.77
A8: FujiFilm FinePix F30 | B8: 9038.52 | C8: =ROUND(B8 / 'Курсы валют'!$B$1, 2) -> 138.84 | D8: =ROUND(B8 / 'Курсы валют'!$B$2, 2) -> 123.9
A9: FujiFilm FinePix A700 | B9: 5079.28 | C9: =ROUND(B9 / 'Курсы валют'!$B$1, 2) -> 78.02 | D9: =ROUND(B9 / 'Курсы валют'!$B$2, 2) -> 69.63
A10: Nikon D70S 18-70 KIT | B10: 27792.79 | C10: =ROUND(B10 / 'Курсы валют'!$B$1, 2) -> 426.92 | D10: =ROUND(B10 / 'Курсы валют'!$B$2, 2) -> 380.98
A11: Nikon CoolPix S10 | B11: 9819.95 | C11: =ROUND(B11 / 'Курсы валют'!$B$1, 2) -> 150.84 | D11: =ROUND(B11 / 'Курсы валют'!$B$2, 2) -> 134.61
A12: OLYMPUS DIGITAL E-330 ZUIKO | B12: 20369.22 | C12: =ROUND(B12 / 'Курсы валют'!$B$1, 2) -> 312.89 | D12: =ROUND(B12 / 'Курсы валют'!$B$2, 2) -> 279.22
A13: OLYMPUS mJU 750 | B13: 9064.56 | C13: =ROUND(B13 / 'Курсы валют'!$B$1, 2) -> 139.24 | D13: =ROUND(B13 / 'Курсы валют'!$B$2, 2) -> 124.26
A14: Panasonic Lumix Dmc-LZ5-S | B14: 6954.71 | C14: =ROUND(B14 / 'Курсы валют'!$B$1, 2) -> 106.83 | D14: =ROUND(B14 / 'Курсы валют'!$B$2, 2) -> 95.34
... A23: Casio EX-S600 Exilm | B23: 8048.71 | C23: =ROUND(B23 / 'Курсы валют'!$B$1, 2) -> 123.64 | D23: =ROUND(B23 / 'Курсы валют'!$B$2, 2) -> 110.33
A24: Итого | B24: =SUM(B3:B23) -> 227656.03 | C24: =SUM(C3:C23) -> 3496.99 | D24: =SUM(D3:D23) -> 3120.72

Sheet Задание 3
A1: Задание: | B1: Вывести суммы по продажам в 3 таблицы справа на основе предоставленных данных | F1: По регионам
A2: Регион | B2: Квартал | C2: Код дистрибьютора | D2: Продажи | F2: Регион | G2: Продажи
A3: Юго-Западный | B3: Первый | C3: H | D3: 165663 | F3: Юго-Западный | G3: =SUMPRODUCT(SUBSTITUTE(D$3:D$35, "р.", "")*(A$3:A$35=F3)) -> 1540875
A4: Юго-Западный | B4: Второй | C4: H | D4: 159002 | F4: Южный | G4: =SUMPRODUCT(SUBSTITUTE(D$3:D$35, "р.", "")*(A$3:A$35=F4)) -> 1409544
A5: Юго-Западный | B5: Третий | C5: H | D5: 180567 | F5: Западный | G5: =SUMPRODUCT(SUBSTITUTE(D$3:D$35, "р.", "")*(A$3:A$35=F5)) -> 1477884
A6: Юго-Западный | B6: Четвертый | C6: H | D6: 200000 | F6: Восточный | G6: =SUMPRODUCT(SUBSTITUTE(D$3:D$35, "р.", "")*(A$3:A$35=F6)) -> 1463655
A7: Юго-Западный | B7: Четвертый | C7: H | D7: 175660
A8: Западный | B8: Первый | C8: G | D8: 200767 | F8: По кварталам
A9: Западный | B9: Второй | C9: G | D9: 190290 | F9: Квартал | G9: Продажи
A10: Западный | B10: Третий | C10: G | D10: 155557 | F10: Первый | G10: =SUMPRODUCT(SUBSTITUTE(D$3:D$35, "р.", "")*(B$3:B$35=F10)) -> 1456780
A11: Западный | B11: Четвертый | C11: G | D11: 148990 | F11: Второй | G11: =SUMPRODUCT(SUBSTITUTE(D$3:D$35, "р.", "")*(B$3:B$35=F11)) -> 1373190
A12: Южный | B12: Первый | C12: F | D12: 180567 | F12: Третий | G12: =SUMPRODUCT(SUBSTITUTE(D$3:D$35, "р.", "")*(B$3:B$35=F12)) -> 1471660
A13: Южный | B13: Второй | C13: F | D13: 175660 | F13: Четвертый | G13: =SUMPRODUCT(SUBSTITUTE(D$3:D$35, "р.", "")*(B$3:B$35=F13)) -> 1590328
A14: Южный | B14: Третий | C14: F | D14: 165778
A15: Южный | B15: Четвертый | C15: F | D15: 155339 | F15: По регионам и кварталу
A16: Юго-Западный | B16: Первый | C16: E | D16: 155557 | F16: Продажи | G16: Квартал
A17: Юго-Западный | B17: Второй | C17: E | D17: 148990 | F17: Регион | G17: Первый | H17: Продажи
A18: Юго-Западный | B18: Третий | C18: E | D18: 185223 | F18: Юго-Западный | G18: =SUMPRODUCT(SUBSTITUTE(D$3:D$35, "р.", "")*(A$3:A$35=F18)*(B$3:B$35=G$17)) -> 321220
A19: Юго-Западный | B19: Четвертый | C19: E | D19: 170213 | F19: Южный | G19: =SUMPRODUCT(SUBSTITUTE(D$3:D$35, "р.", "")*(A$3:A$35=F19)*(B$3:B$35=G$17)) -> 346345
A20: Южный | B20: Первый | C20: D | D20: 165778 | F20: Западный | G20: =SUMPRODUCT(SUBSTITUTE(D$3:D$35, "р.", "")*(A$3:A$35=F20)*(B$3:B$35=G$17)) -> 411647
A21: Южный | B21: Второй | C21: D | D21: 155339 | F21: Восточный | G21: =SUMPRODUCT(SUBSTITUTE(D$3:D$35, "р.", "")*(A$3:A$35=F21)*(B$3:B$35=G$17)) -> 377568
A22: Южный | B22: Третий | C22: D | D22: 210880
A23: Южный | B23: Четвертый | C23: D | D23: 200203
A24: Восточный | B24: Первый | C24: C | D24: 185223
A25: Восточный | B25: Второй | C25: C | D25: 170213
A26: Восточный | B26: Третий | C26: C | D26: 192345
A27: Восточный | B27: Четвертый | C27: C | D27: 173493
A28: Западный | B28: Первый | C28: B | D28: 210880
A29: Западный | B29: Второй | C29: B | D29: 200203
A30: Западный | B30: Третий | C30: B | D30: 205534
A31: Западный | B31: Четвертый | C31: B | D31: 165663
A32: Восточный | B32: Первый | C32: A | D32: 192345
A33: Восточный | B33: Второй | C33: A | D33: 173493
... A35: Восточный | B35: Четвертый | C35: A | D35: 200767

Sheet Задание 4
A1: Задание: | B1: Вывести количество сотрудников в сооветствии с заголовками таблиц на основе предоставленных данных
A2: ФИО | B2: Пол | C2: Должность | D2: Оклад | E2: Компания | G2: Количество сотрудников по должностям
A3: ФИО1 | B3: ж | C3: Менеджер | D3: =IF(C3="Менеджер",400000,IF(C3="Эксперт",95000,IF(C3="Юрист",65000,75000))) -> 400000 | E3: Внедрение | G3: Должность | H3: Кол-во
A4: ФИО2 | B4: м | C4: Менеджер | D4: =IF(C4="Менеджер",400000,IF(C4="Эксперт",95000,IF(C4="Юрист",65000,75000))) -> 400000 | E4: Внедрение | G4: Менеджер | H4: =COUNTIF(C$3:C$88,G4) -> 71
A5: ФИО3 | B5: ж | C5: Эксперт | D5: =IF(C5="Менеджер",400000,IF(C5="Эксперт",95000,IF(C5="Юрист",65000,75000))) -> 95000 | E5: Информ | G5: Эксперт | H5: =COUNTIF(C$3:C$88,G5) -> 8
A6: ФИО4 | B6: ж | C6: Менеджер | D6: =IF(C6="Менеджер",400000,IF(C6="Эксперт",95000,IF(C6="Юрист",65000,75000))) -> 400000 | E6: Квалификация | G6: Юрист | H6: =COUNTIF(C$3:C$88,G6) -> 5
A7: ФИО5 | B7: ж | C7: Менеджер | D7: =IF(C7="Менеджер",400000,IF(C7="Эксперт",95000,IF(C7="Юрист",65000,75000))) -> 400000 | E7: Информ | G7: Аудитор | H7: =COUNTIF(C$3:C$88,G7) -> 2
A8: ФИО6 | B8: м | C8: Менеджер | D8: =IF(C8="Менеджер",400000,IF(C8="Эксперт",95000,IF(C8="Юрист",65000,75000))) -> 400000 | E8: Информ
A9: ФИО7 | B9: ж | C9: Юрист | D9: =IF(C9="Менеджер",400000,IF(C9="Эксперт",95000,IF(C9="Юрист",65000,75000))) -> 65000 | E9: Аудит | G9: Кол-во сотрудников-мужчин в компаниях
A10: ФИО8 | B10: ж | C10: Менеджер | D10: =IF(C10="Менеджер",400000,IF(C10="Эксперт",95000,IF(C10="Юрист",65000,75000))) -> 400000 | E10: Информ | G10: БЕ | H10: м
A11: ФИО9 | B11: ж | C11: Менеджер | D11: =IF(C11="Менеджер",400000,IF(C11="Эксперт",95000,IF(C11="Юрист",65000,75000))) -> 400000 | E11: Информ | G11: Внедрение | H11: =COUNTIFS(E$3:E$88,G11,B$3:B$88,H$10) -> 7
A12: ФИО10 | B12: ж | C12: Менеджер | D12: =IF(C12="Менеджер",400000,IF(C12="Эксперт",95000,IF(C12="Юрист",65000,75000))) -> 400000 | E12: Информ | G12: Информ | H12: =COUNTIFS(E$3:E$88,G12,B$3:B$88,H$10) -> 19
A13: ФИО11 | B13: ж | C13: Менеджер | D13: =IF(C13="Менеджер",400000,IF(C13="Эксперт",95000,IF(C13="Юрист",65000,75000))) -> 400000 | E13: Информ | G13: Квалификация | H13: =COUNTIFS(E$3:E$88,G13,B$3:B$88,H$10) -> 1
A14: ФИО12 | B14: ж | C14: Менеджер | D14: =IF(C14="Менеджер",400000,IF(C14="Эксперт",95000,IF(C14="Юрист",65000,75000))) -> 400000 | E14: Информ | G14: Аудит | H14: =COUNTIFS(E$3:E$88,G14,B$3:B$88,H$10) -> 0
A15: ФИО13 | B15: ж | C15: Менеджер | D15: =IF(C15="Менеджер",400000,IF(C15="Эксперт",95000,IF(C15="Юрист",65000,75000))) -> 400000 | E15: Информ | G15: Оценка | H15: =COUNTIFS(E$3:E$88,G15,B$3:B$88,H$10) -> 0
A16: ФИО14 | B16: м | C16: Юрист | D16: =IF(C16="Менеджер",400000,IF(C16="Эксперт",95000,IF(C16="Юрист",65000,75000))) -> 65000 | E16: Информ
A17: ФИО15 | B17: ж | C17: Менеджер | D17: =IF(C17="Менеджер",400000,IF(C17="Эксперт",95000,IF(C17="Юрист",65000,75000))) -> 400000 | E17: Информ
A18: ФИО16 | B18: ж | C18: Менеджер | D18: =IF(C18="Менеджер",400000,IF(C18="Эксперт",95000,IF(C18="Юрист",65000,75000))) -> 400000 | E18: Информ
A19: ФИО17 | B19: ж | C19: Менеджер | D19: =IF(C19="Менеджер",400000,IF(C19="Эксперт",95000,IF(C19="Юрист",65000,75000))) -> 400000 | E19: Информ
A20: ФИО18 | B20: ж | C20: Эксперт | D20: =IF(C20="Менеджер",400000,IF(C20="Эксперт",95000,IF(C20="Юрист",65000,75000))) -> 95000 | E20: Квалификация
A21: ФИО19 | B21: ж | C21: Менеджер | D21: =IF(C21="Менеджер",400000,IF(C21="Эксперт",95000,IF(C21="Юрист",65000,75000))) -> 400000 | E21: Информ
A22: ФИО20 | B22: ж | C22: Менеджер | D22: =IF(C22="Менеджер",400000,IF(C22="Эксперт",95000,IF(C22="Юрист",65000,75000))) -> 400000 | E22: Внедрение
A23: ФИО21 | B23: ж | C23: Менеджер | D23: =IF(C23="Менеджер",400000,IF(C23="Эксперт",95000,IF(C23="Юрист",65000,75000))) -> 400000 | E23: Информ
A24: ФИО22 | B24: м | C24: Менеджер | D24: =IF(C24="Менеджер",400000,IF(C24="Эксперт",95000,IF(C24="Юрист",65000,75000))) -> 400000 | E24: Информ
A25: ФИО23 | B25: ж | C25: Эксперт | D25: =IF(C25="Менеджер",400000,IF(C25="Эксперт",95000,IF(C25="Юрист",65000,75000))) -> 95000 | E25: Квалификация
A26: ФИО24 | B26: ж | C26: Эксперт | D26: =IF(C26="Менеджер",400000,IF(C26="Эксперт",95000,IF(C26="Юрист",65000,75000))) -> 95000 | E26: Аудит
A27: ФИО25 | B27: ж | C27: Менеджер | D27: =IF(C27="Менеджер",400000,IF(C27="Эксперт",95000,IF(C27="Юрист",65000,75000))) -> 400000 | E27: Внедрение
... A88: ФИО86 | B88: ж | C88: Юрист | D88: =IF(C88="Менеджер",400000,IF(C88="Эксперт",95000,IF(C88="Юрист",65000,75000))) -> 65000 | E88: Информ

Sheet Дата
A1: Текущая дата
A2: Текущее время
A4: Количество дней между
A5: Дата начала | B5: Дата окончания | C5: Разница
A6: 41744 | B6: 41773

Sheet Задание 5
A1: Задание: | B1: Удалить "лишние" пробелы из столбца "А"
A2: Фамилия Имя Отчество | B2: Фамилия Имя Отчество
A3: Колесник Мария Степановна | B3: =TRIM(A3) -> Колесник Мария Степановна
A4: Шарандак Галина Константиновна | B4: =TRIM(A4) -> Шарандак Галина Константиновна
A5: Дидковская Елена Владимировна | B5: =TRIM(A5) -> Дидковская Елена Владимировна
A6: Самохина Надежда Романовна | B6: =TRIM(A6) -> Самохина Надежда Романовна
A7: Давидчук Ольга Петровна | B7: =TRIM(A7) -> Давидчук Ольга Петровна
A8: Черненькая Ольга Николаевна | B8: =TRIM(A8) -> Черненькая Ольга Николаевна
A9: Кацовец Татьяна Михайловна | B9: =TRIM(A9) -> Кацовец Татьяна Михайловна
A10: Искоростенская Зоя Николаевна | B10: =TRIM(A10) -> Искоростенская Зоя Николаевна

Sheet Задание 6
D1: 1. Разнести фамилию, имя и отчество по трем разным столбцам, используя встроенную функцию Excel
A2: № п/п | B2: ФИО | D2: № п/п | E2: Фамилия | F2: Имя | G2: Отчество
A3: 1 | B3: Колесник Мария Степановна | D3: 1 | E3: =ТЕКСТРАЗД(B3, " ") -> #NAME?
A4: 2 | B4: Шарандак Галина Константиновна | D4: 2
A5: 3 | B5: Дидковская Елена Владимировна | D5: 3
A6: 4 | B6: Самохина Надежда Романовна | D6: 4
A7: 5 | B7: Давидчук Ольга Петровна | D7: 5
A8: 6 | B8: Черненькая Ольга Николаевна | D8: 6
A9: 7 | B9: Кацовец Татьяна Михайловна | D9: 7
A10: 8 | B10: Искоростенская Зоя Николаевна | D10: 8
D13: 2. Разнести фамилию, имя и отчество по трем разным столбцам, используя набор функций по работе со строками
D14: № п/п | E14: Фамилия | F14: Имя | G14: Отчество
D15: 1 | E15: =LEFT(B3, FIND(" ", B3)-1) -> Колесник | F15: =MID(B3, FIND(" ", B3)+1, FIND(" ", B3, FIND(" ", B3)+1) - FIND(" ", B3)-1) -> Мария | G15: =RIGHT(B3, LEN(B3) - FIND(" ", B3, FIND(" ", B3)+1)) -> Степановна
D16: 2 | E16: =LEFT(B4, FIND(" ", B4)-1) -> Шарандак | F16: =MID(B4, FIND(" ", B4)+1, FIND(" ", B4, FIND(" ", B4)+1) - FIND(" ", B4)-1) -> Галина | G16: =RIGHT(B4, LEN(B4) - FIND(" ", B4, FIND(" ", B4)+1)) -> Константиновна
D17: 3 | E17: =LEFT(B5, FIND(" ", B5)-1) -> Дидковская | F17: =MID(B5, FIND(" ", B5)+1, FIND(" ", B5, FIND(" ", B5)+1) - FIND(" ", B5)-1) -> Елена | G17: =RIGHT(B5, LEN(B5) - FIND(" ", B5, FIND(" ", B5)+1)) -> Владимировна
D18: 4 | E18: =LEFT(B6, FIND(" ", B6)-1) -> Самохина | F18: =MID(B6, FIND(" ", B6)+1, FIND(" ", B6, FIND(" ", B6)+1) - FIND(" ", B6)-1) -> Надежда | G18: =RIGHT(B6, LEN(B6) - FIND(" ", B6, FIND(" ", B6)+1)) -> Романовна
D19: 5 | E19: =LEFT(B7, FIND(" ", B7)-1) -> Давидчук | F19: =MID(B7, FIND(" ", B7)+1, FIND(" ", B7, FIND(" ", B7)+1) - FIND(" ", B7)-1) -> Ольга | G19: =RIGHT(B7, LEN(B7) - FIND(" ", B7, FIND(" ", B7)+1)) -> Петровна
D20: 6 | E20: =LEFT(B8, FIND(" ", B8)-1) -> Черненькая | F20: =MID(B8, FIND(" ", B8)+1, FIND(" ", B8, FIND(" ", B8)+1) - FIND(" ", B8)-1) -> Ольга | G20: =RIGHT(B8, LEN(B8) - FIND(" ", B8, FIND(" ", B8)+1)) -> Николаевна
D21: 7 | E21: =LEFT(B9, FIND(" ", B9)-1) -> Кацовец | F21: =MID(B9, FIND(" ", B9)+1, FIND(" ", B9, FIND(" ", B9)+1) - FIND(" ", B9)-1) -> Татьяна | G21: =RIGHT(B9, LEN(B9) - FIND(" ", B9, FIND(" ", B9)+1)) -> Михайловна
D22: 8 | E22: =LEFT(B10, FIND(" ", B10)-1) -> Искоростенская | F22: =MID(B10, FIND(" ", B10)+1, FIND(" ", B10, FIND(" ", B10)+1) - FIND(" ", B10)-1) -> Зоя | G22: =RIGHT(B10, LEN(B10) - FIND(" ", B10, FIND(" ", B10)+1)) -> Николаевна

Sheet Задание 7
A1: Задание: | B1: Используя данные таблицы, необходимо заполнить столбец "Рентабельность" по следующим условиям:
B2: Если уровень продаж той или иной марки составляет не менее 8% от общего уровня, то необходимо в столбце отображать "да", иначе - "нет"
A3: Марка | B3: Подажи (млн.шт.) | C3: Доля продаж (%) | D3: Рентабельность (да/нет)
A4: DIRF-500 | B4: 1.01 | C4: =B4/SUM($B$4:$B$17) -> 0.05276907 | D4: =IF(C4 >= 8%, "да", "нет") -> нет
A5: DIRF-510A | B5: 1.2 | C5: =B5/SUM($B$4:$B$17) -> 0.062695925 | D5: =IF(C5 >= 8%, "да", "нет") -> нет
A6: Sony V800 | B6: 1.9 | C6: =B6/SUM($B$4:$B$17) -> 0.099268548 | D6: =IF(C6 >= 8%, "да", "нет") -> да
A7: Sony V900 | B7: 1.95 | C7: =B7/SUM($B$4:$B$17) -> 0.10188088 | D7: =IF(C7 >= 8%, "да", "нет") -> да
A8: Sony V950 | B8: 1.76 | C8: =B8/SUM($B$4:$B$17) -> 0.091954023 | D8: =IF(C8 >= 8%, "да", "нет") -> да
A9: Sony Extra (class M) | B9: 0.95 | C9: =B9/SUM($B$4:$B$17) -> 0.049634274 | D9: =IF(C9 >= 8%, "да", "нет") -> нет
A10: YoYs G1 | B10: 0.4 | C10: =B10/SUM($B$4:$B$17) -> 0.020898642 | D10: =IF(C10 >= 8%, "да", "нет") -> нет
A11: YoYs G2 | B11: 0.45 | C11: =B11/SUM($B$4:$B$17) -> 0.023510972 | D11: =IF(C11 >= 8%, "да", "нет") -> нет
A12: SMSNG P1 | B12: 2.1 | C12: =B12/SUM($B$4:$B$17) -> 0.10971787 | D12: =IF(C12 >= 8%, "да", "нет") -> да
A13: SMSNG P2 | B13: 2.01 | C13: =B13/SUM($B$4:$B$17) -> 0.10501567 | D13: =IF(C13 >= 8%, "да", "нет") -> да
A14: SMSNG P3 | B14: 2.7 | C14: =B14/SUM($B$4:$B$17) -> 0.14106583 | D14: =IF(C14 >= 8%, "да", "нет") -> да
A15: Gion Future | B15: 0.8 | C15: =B15/SUM($B$4:$B$17) -> 0.041797283 | D15: =IF(C15 >= 8%, "да", "нет") -> нет
... A17: Seo Mu 5 | B17: 0.99 | C17: =B17/SUM($B$4:$B$17) -> 0.051724138 | D17: =IF(C17 >= 8%, "да", "нет") -> нет

Sheet Если 2
A1: Заказы клиентов на поставку товаров
A2: Клиенты | B2: Стоимость заказа, $ | C2: Количество наименований в заказе | D2: Бонус | E2: Купон на скидку | F2: Скидка, $ | H2: Бонус | I2: Купон на скидку | J2: Скидка, $
A3: Ростикс | B3: 800 | C3: 10 | I3: + | J3: 120
A4: Му-Му | B4: 600 | C4: 8 | J4: 90
A5: Макдональдс | B5: 1200 | C5: 15 | H5: да | I5: + | J5: 216
A6: Шоколадница | B6: 1000 | C6: 6 | I6: + | J6: 180
A7: Патио-пицца | B7: 1500 | C7: 7 | I7: + | J7: 315
A8: Кофе-хауз | B8: 700 | C8: 5 | J8: 105
A9: Елки-палки | B9: 1100 | C9: 12 | H9: да | I9: + | J9: 198
A10: Русское бистро | B10: 1300 | C10: 14 | H10: да | I10: + | J10: 273

Sheet Задание 8
A1: Задание: | B1: Используя данные таблиц справа заполнить столбцы "Сумма", "Скидка" и "Сумма с учетом скидки"
B2: Запись формульного выражения должна быть универсальной. Формула не меняется, если добавить новые уровни в таблицу "Таблица_Диапазонов"
A3: Покупатель | B3: Наименование | C3: Количество | D3: Сумма | E3: Скидка | F3: Сумма с учетом скидки | H3: Наименование | I3: Цена за шт. | K3: Количество от | L3: Скидка
A4: АО "Книга" | B4: компьютер | C4: 4 | D4: =C4 * SUMIF(H$4:H$7, B4, I$4:I$7) -> 2000 | H4: компьютер | I4: 500 | K4: 0 | L4: 0.02
A5: Фирма "Астра" | B5: компьютер | C5: 6 | D5: =C5 * SUMIF(H$4:H$7, B5, I$4:I$7) -> 3000 | H5: принтер | I5: 300 | K5: 5 | L5: 0.07
A6: ООО "Консул" | B6: модем | C6: 6 | D6: =C6 * SUMIF(H$4:H$7, B6, I$4:I$7) -> 900 | H6: сканер | I6: 250 | K6: 10 | L6: 0.09
A7: ТД "Северный" | B7: принтер | C7: 3 | D7: =C7 * SUMIF(H$4:H$7, B7, I$4:I$7) -> 900 | H7: модем | I7: 150 | K7: 20 | L7: 0.15
A8: АО "Трейд-Инвест" | B8: модем | C8: 10 | D8: =C8 * SUMIF(H$4:H$7, B8, I$4:I$7) -> 1500 | K8: 30 | L8: 0.16
A9: Фирма "Контур-М" | B9: модем | C9: 2 | D9: =C9 * SUMIF(H$4:H$7, B9, I$4:I$7) -> 300 | K9: 40 | L9: 0.17
A10: Фирма "Консалтинг" | B10: компьютер | C10: 6 | D10: =C10 * SUMIF(H$4:H$7, B10, I$4:I$7) -> 3000 | K10: 50 | L10: 0.18
A11: Фирма "Лютики" | B11: принтер | C11: 25 | D11: =C11 * SUMIF(H$4:H$7, B11, I$4:I$7) -> 7500 | K11: 60 | L11: 0.19
A12: Фирма "Гвоздика" | B12: модем | C12: 37 | D12: =C12 * SUMIF(H$4:H$7, B12, I$4:I$7) -> 5550
A13: Фирма "Ромашка" | B13: модем | C13: 42 | D13: =C13 * SUMIF(H$4:H$7, B13, I$4:I$7) -> 6300
A14: Фирма "Хризантема" | B14: компьютер | C14: 65 | D14: =C14 * SUMIF(H$4:H$7, B14, I$4:I$7) -> 32500
A15: ИТОГО

Sheet Задание 10
A1: Задание: | B1: Определите Регион поставки и клиента по артикулу товара, набранному в ячейку J3.
A2: № | B2: Регион | C2: Клиент | D2: Артикул товара | E2: Кол-во | F2: Цена | G2: Сумма
A3: 1 | B3: Москва | C3: Иванов | D3: 8985 | E3: 95 | F3: 598 | G3: =F3*E3 -> 56810 | I3: Артикул | J3: 3227
A4: 2 | B4: Питер | C4: Петров | D4: 8067 | E4: 50 | F4: 582 | G4: =F4*E4 -> 29100 | I4: Регион | J4: =INDEX(B$3:B$14,MATCH(J3,D$3:D$14,0)) -> Орск
A5: 3 | B5: Вологда | C5: Сидоров | D5: 4901 | E5: 36 | F5: 562 | G5: =F5*E5 -> 20232 | I5: Клиент | J5: =INDEX(C$3:C$14, MATCH(J3, D$3:D$14, 0)) -> Щеглов
A6: 4 | B6: Самара | C6: Михайлов | D6: 9096 | E6: 27 | F6: 543 | G6: =F6*E6 -> 14661
A7: 5 | B7: Сургут | C7: Тарасов | D7: 9604 | E7: 100 | F7: 687 | G7: =F7*E7 -> 68700
A8: 6 | B8: Новгород | C8: Кузнецов | D8: 4233 | E8: 60 | F8: 961 | G8: =F8*E8 -> 57660
A9: 7 | B9: Тамбов | C9: Березин | D9: 6576 | E9: 12 | F9: 614 | G9: =F9*E9 -> 7368
A10: 8 | B10: Магадан | C10: Теркин | D10: 8791 | E10: 90 | F10: 950 | G10: =F10*E10 -> 85500
A11: 9 | B11: Чита | C11: Степанов | D11: 7605 | E11: 32 | F11: 896 | G11: =F11*E11 -> 28672
A12: 10 | B12: Орск | C12: Щеглов | D12: 3227 | E12: 60 | F12: 670 | G12: =F12*E12 -> 40200
A13: 11 | B13: Челябинск | C13: Шоркин | D13: 5854 | E13: 29 | F13: 603 | G13: =F13*E13 -> 17487
A14: 12 | B14: Новосибирск | C14: Баранов | D14: 6433 | E14: 35 | F14: 755 | G14: =F14*E14 -> 26425

Sheet Задание 11
A1: Задание: | B1: Используя функцию Excel заменить код ошибки #Н/Д в поле Премия на числовое значение - 0.
A2: № | B2: Ф.И.О. | C2: Отдел | D2: Оклад, руб | E2: Премия
A3: 1 | B3: Ангелочкин Антон Алексеевич | C3: ОТД | D3: 55000 | E3: =IFERROR(D3*VLOOKUP(C3,$G$4:$H$7,2,0),0) -> 33000 | G3: отдел | H3: Коэффициент
A4: 2 | B4: Везунчиков Виктор Васильевич | C4: ОНК | D4: 42000 | E4: =IFERROR(D4*VLOOKUP(C4,$G$4:$H$7,2,0),0) -> 33600 | G4: ОНК | H4: 0.8
A5: 3 | B5: Веселый Василий Викторович | C5: ОТД | D5: 45000 | E5: =IFERROR(D5*VLOOKUP(C5,$G$4:$H$7,2,0),0) -> 27000 | G5: ОТД | H5: 0.6
A6: 4 | B6: Добрейший Даниил Дмитриевич | C6: РМО | D6: 65000 | E6: =IFERROR(D6*VLOOKUP(C6,$G$4:$H$7,2,0),0) -> 0 | G6: ТКБ | H6: 0.4
A7: 5 | B7: Добрецов Денис Давидович | C7: ОКЧ | D7: 70000 | E7: =IFERROR(D7*VLOOKUP(C7,$G$4:$H$7,2,0),0) -> 35000 | G7: ОКЧ | H7: 0.5
A8: 6 | B8: Душечкин Дмитрий Данилович | C8: ТКБ | D8: 75000 | E8: =IFERROR(D8*VLOOKUP(C8,$G$4:$H$7,2,0),0) -> 30000
A9: 7 | B9: Замечательная Зинаида Захаровна | C9: ОНК | D9: 33000 | E9: =IFERROR(D9*VLOOKUP(C9,$G$4:$H$7,2,0),0) -> 26400
A10: 8 | B10: Красавцев Константин Кириллович | C10: ТКБ | D10: 45000 | E10: =IFERROR(D10*VLOOKUP(C10,$G$4:$H$7,2,0),0) -> 18000
A11: 9 | B11: Мирный Максим Михайлович | C11: ОМА | D11: 50000 | E11: =IFERROR(D11*VLOOKUP(C11,$G$4:$H$7,2,0),0) -> 0
A12: 10 | B12: Неунывающий Никита Николаевич | C12: ТКБ | D12: 60000 | E12: =IFERROR(D12*VLOOKUP(C12,$G$4:$H$7,2,0),0) -> 24000
A13: 11 | B13: Оптимистов Олег Осипович | C13: ОТД | D13: 48000 | E13: =IFERROR(D13*VLOOKUP(C13,$G$4:$H$7,2,0),0) -> 28800
A14: 12 | B14: Отличницева Оксана Олеговна | C14: ОНК | D14: 35000 | E14: =IFERROR(D14*VLOOKUP(C14,$G$4:$H$7,2,0),0) -> 28000
A15: 13 | B15: Позитивов Платон Петрович | C15: ТКБ | D15: 40000 | E15: =IFERROR(D15*VLOOKUP(C15,$G$4:$H$7,2,0),0) -> 16000
A16: 14 | B16: Праздникова Полина Павловна | C16: ОМА | D16: 55000 | E16: =IFERROR(D16*VLOOKUP(C16,$G$4:$H$7,2,0),0) -> 0
A17: 15 | B17: Прекрасная Пелагея Платоновна | C17: ОТД | D17: 36000 | E17: =IFERROR(D17*VLOOKUP(C17,$G$4:$H$7,2,0),0) -> 21600
A18: 16 | B18: Приятный Павел Петрович | C18: ОКЧ | D18: 58000 | E18: =IFERROR(D18*VLOOKUP(C18,$G$4:$H$7,2,0),0) -> 29000
A19: 17 | B19: Радостная Раиса Романовна | C19: ОТД | D19: 49000 | E19: =IFERROR(D19*VLOOKUP(C19,$G$4:$H$7,2,0),0) -> 29400
... A25: 23 | B25: Хороших Харитон Харитонович | C25: ОТД | D25: 54000 | E25: =IFERROR(D25*VLOOKUP(C25,$G$4:$H$7,2,0),0) -> 32400

Sheet Задание 12
A1: Задание: | B1: Сделайте 2 сводные таблицы на основе данных с Листа "Данные" по предоставленным образцам

Sheet Задание 13

Sheet Задание 14
A1: Задание 1:
A9: Задание 2:

Sheet Задание 15

Sheet Анализ
B1: Контракты, шт | F1: Продажа контрактов по регионам, шт
B2: Янв | C2: 121 | F2: Регион | G2: 1 кв | H2: 2 кв | I2: 3 кв | J2: 4 кв
B3: Фев | C3: 195 | F3: Север | G3: 1034 | H3: 1529 | I3: 1221 | J3: 2804
B4: Мар | C4: 461 | F4: Восток | G4: 912 | H4: 923 | I4: 703 | J4: 798
B5: Апр | C5: 367 | F5: Центр | G5: 2222 | H5: 1881 | I5: 1441 | J5: 1112
B6: Май | C6: 159 | F6: Юг | G6: 1606 | H6: 809 | I6: 911 | J6: 999
B7: Июн | C7: 97 | F7: Запад | G7: 905 | H7: 823 | I7: 613 | J7: 555
B8: Июл | C8: 199
B9: Авг | C9: 253
B10: Сен | C10: 402
B11: Окт | C11: 306
B12: Ноя | C12: 249
B13: Дек | C13: 161

Sheet Инфокривые
A1: Динамика курсов валют с 31.03.2008 по 31.03.2010
A3: Дата | B3: 31.03.2008 | C3: 30.06.2008 | D3: 30.09.2008 | E3: 31.12.2008 | F3: 31.03.2009 | G3: 30.06.2009 | H3: 30.09.2009 | I3: 31.12.2009 | J3: 31.03.2010
A4: Лит | B4: 10.733 | C4: 10.6663 | D4: 10.5656 | E4: 12.0377 | F4: 13.1362 | G4: 12.6616 | H4: 12.7727 | I4: 12.4325 | J4: 11.5017
A5: Гривня | B5: 4.66256 | C5: 4.95654 | D5: 4.99434 | E5: 3.8557 | F5: 4.22527 | G5: 4.07427 | H5: 3.56332 | I5: 3.76172 | J5: 3.70568
A6: Иена | B6: 0.235698 | C6: 0.219597 | D6: 0.237189 | E6: 0.325779 | F6: 0.353551 | G6: 0.327751 | H6: 0.323298 | I6: 0.32826 | J6: 0.31695
A7: Евро | B7: 37.0676 | C7: 36.9077 | D7: 36.37 | E7: 41.4411 | F7: 44.9419 | G7: 43.8191 | H7: 43.218 | I7: 43.3883 | J7: 39.7028
A8: Доллар | B8: 23.5156 | C8: 23.4573 | D8: 25.2464 | E8: 29.3804 | F8: 34.0134 | G8: 31.2904 | H8: 29.3441 | I8: 30.2442 | J8: 29.3638

Sheet Смешанная диаграмма
A1: Период | B1: Расход | C1: Доход | D1: Продажи | E1: Закупки | F1: Средний бал
A2: 1 квартал | B2: 3 | C2: 3 | D2: 9 | E2: 7 | F2: =AVERAGE(B2:E2) -> 5.5
A3: 2 квартал | B3: 9 | C3: 4 | D3: 3 | E3: 8 | F3: =AVERAGE(B3:E3) -> 6
A4: 3 квартал | B4: 8 | C4: 6 | D4: 10 | E4: 6 | F4: =AVERAGE(B4:E4) -> 7.5
A5: 4 квартал | B5: 2 | C5: 10 | D5: 8 | E5: 5 | F5: =AVERAGE(B5:E5) -> 6.25
